[
    {
        "no": "5",
        "img" : "/data/yuhancare/inc/img_new/culture/people/interview_5.jpg",
        "team" : "천연물연구소2팀",
        "class" : "연구원",
        "title" : "유한천연물라이브러리는 우리가 만든다!",
        "name" : "김성은 과장"
    },
    {
        "no": "4",
        "img" : "/data/yuhancare/inc/img_new/culture/people/interview_4.jpg",
        "team" : "천연물연구소2팀",
        "class" : "연구원",
        "title" : "천연물연구를 위한 끝없는 노력!",
        "name" : "안선미 과장"
    },
    {
        "no": "3",
        "img" : "/data/yuhancare/inc/img_new/culture/people/interview_3.jpg",
        "team" : "이커머스팀",
        "class" : "MD",
        "title" : "온라인에서 수많은 고객을 만나다!",
        "name" : "강지현 대리"
    },
    {
        "no": "2",
        "img" : "/data/yuhancare/inc/img_new/culture/people/interview_2.jpg",
        "team" : "RM팀",
        "class" : "SCM",
        "title" : "회사의 모든 자산을 원활하게 움직이는 곳!",
        "name" : "유창석 과장"
    },
    {
        "no": "1",
        "img" : "/data/yuhancare/inc/img_new/culture/people/interview_1.jpg",
        "team" : "BDM팀",
        "class" : "BM",
        "title" : "내 제품을 내 자식과 같이~!",
        "name" : "나지연 과장"
    }
]